{
  "RETURN_CODE": 1,
  "RETURN_DESCRIPTION": "İşlem Başarılı.",
  "RETURN_TABLE": [
    { "YEMEKHANE_ID": 46.0, "YEMEKHANE_ADI": "KEMAH MYO", "DOLULUK_ORANI": 0.0 },
    { "YEMEKHANE_ID": 47.0, "YEMEKHANE_ADI": "ÇAYIRLI MYO", "DOLULUK_ORANI": 0.0 },
    { "YEMEKHANE_ID": 48.0, "YEMEKHANE_ADI": "İLİÇ MYO", "DOLULUK_ORANI": 0.0 },
    { "YEMEKHANE_ID": 49.0, "YEMEKHANE_ADI": "SAĞLIK BİLİMLERİ FAKÜLTESİ", "DOLULUK_ORANI": 0.0 },
    { "YEMEKHANE_ID": 50.0, "YEMEKHANE_ADI": "Tercan Meslek Yüksekokulu", "DOLULUK_ORANI": 0.0 },
    { "YEMEKHANE_ID": 52.0, "YEMEKHANE_ADI": "TERCAN MYO", "DOLULUK_ORANI": 0.0 },
    { "YEMEKHANE_ID": 53.0, "YEMEKHANE_ADI": "YALNIZBAĞ YERLEŞKESİ", "DOLULUK_ORANI": 0.0 },
    { "YEMEKHANE_ID": 54.0, "YEMEKHANE_ADI": "ÜZÜMLÜ MYO", "DOLULUK_ORANI": 0.0 },
    { "YEMEKHANE_ID": 55.0, "YEMEKHANE_ADI": "KEMALİYE MYO", "DOLULUK_ORANI": 0.0 },
    { "YEMEKHANE_ID": 56.0, "YEMEKHANE_ADI": "REFAHİYE MYO", "DOLULUK_ORANI": 0.0 },
    { "YEMEKHANE_ID": 58.0, "YEMEKHANE_ADI": "HUKUK FAKÜLTESİ", "DOLULUK_ORANI": 0.0 },
    { "YEMEKHANE_ID": 110.0, "YEMEKHANE_ADI": "DİŞ HEKİMLİĞİ FAKÜLTESİ/ SAĞLIK HİZMETLERİ MYO", "DOLULUK_ORANI": 0.0 },
    { "YEMEKHANE_ID": 302.0, "YEMEKHANE_ADI": "TIP FAKÜLTESİ", "DOLULUK_ORANI": 0.0 }
  ]
}
